{
    "nextId": 11,
    "data": [
        {
            "id": 1,
            "title": "Project 1",
            "description": "Random Description For Project 1",
            "createdAt": "2022-01-20 11:48:20 AM",
            "deadline": "2023-08-25 12:59:59 PM"
        },
        {
            "id": 2,
            "title": "Project 2",
            "description": "Random Description For Project 2",
            "createdAt": "2022-01-20 11:48:20 AM",
            "deadline": "2023-08-25 12:59:59 PM"
        },
        {
            "id": 3,
            "title": "Project 3",
            "description": "Random Description For Project 3",
            "createdAt": "2022-01-20 11:48:20 AM",
            "deadline": "2023-08-25 12:59:59 PM"
        },
        {
            "id": 4,
            "title": "Project 4",
            "description": "Random Description For Project 4",
            "createdAt": "2022-01-20 11:48:20 AM",
            "deadline": "2023-08-25 12:59:59 PM"
        },
        {
            "id": 5,
            "title": "Project 5",
            "description": "Random Description For Project 5",
            "createdAt": "2022-01-20 11:48:20 AM",
            "deadline": "2023-08-25 12:59:59 PM"
        },
        {
            "id": 6,
            "title": "Project 6",
            "description": "Random Description For Project 6",
            "createdAt": "2022-01-20 11:48:20 AM",
            "deadline": "2023-08-25 12:59:59 PM"
        },
        {
            "id": 7,
            "title": "Project 7",
            "description": "Random Description For Project 7",
            "createdAt": "2022-01-20 11:48:20 AM",
            "deadline": "2023-08-25 12:59:59 PM"
        },
        {
            "id": 8,
            "title": "Project 8",
            "description": "Random Description For Project 8",
            "createdAt": "2022-01-20 11:48:20 AM",
            "deadline": "2023-08-25 12:59:59 PM"
        },
        {
            "id": 9,
            "title": "Project 9",
            "description": "Random Description For Project 9",
            "createdAt": "2022-01-20 11:48:20 AM",
            "deadline": "2023-08-25 12:59:59 PM"
        },
        {
            "id": 10,
            "title": "Project 10",
            "description": "Random Description For Project 10",
            "createdAt": "2022-01-20 11:48:20 AM",
            "deadline": "2023-08-25 12:59:59 PM"
        }
    ]
}